streamlit_survey/__init__.py
streamlit_survey/pages.py
streamlit_survey/streamlit_survey.py
streamlit_survey/survey_component.py
streamlit_survey-1.1.0.dist-info/licenses/LICENSE
streamlit_survey-1.1.0.dist-info/METADATA
streamlit_survey-1.1.0.dist-info/WHEEL
streamlit_survey-1.1.0.dist-info/top_level.txt
streamlit_survey-1.1.0.dist-info/RECORD
