Metadata-Version: 2.4
Name: streamlit_survey
Version: 1.1.0
Summary: Survey components for Streamlit apps
Home-page: https://github.com/OlivierBinette/streamlit_survey
Author: Olivier Binette
Author-email: olivier.binette@gmail.com
License: Commons Clause + Apache License 2.0
Keywords: streamlit_survey
Classifier: Development Status :: 2 - Pre-Alpha
Classifier: Intended Audience :: Developers
Classifier: License :: OSI Approved :: Apache Software License
Classifier: Natural Language :: English
Classifier: Programming Language :: Python :: 3
Requires-Python: >=3.6
License-File: LICENSE
Requires-Dist: streamlit>=1.40.0
Dynamic: author
Dynamic: author-email
Dynamic: classifier
Dynamic: description
Dynamic: home-page
Dynamic: keywords
Dynamic: license
Dynamic: license-file
Dynamic: requires-dist
Dynamic: requires-python
Dynamic: summary
